_load_dotenv.py
dotenv_pth-1.0.dist-info/METADATA
dotenv_pth-1.0.dist-info/WHEEL
dotenv_pth-1.0.dist-info/entry_points.txt
load_dotenv_.pth
dotenv_pth-1.0.dist-info/RECORD
