Metadata-Version: 2.1
Name: dotenv.pth
Version: 1.0
Summary: call `load_dotenv()` when python starts
Author-Email: Muspi Merol <me@promplate.dev>
License: MIT
Project-URL: Repository, https://github.com/CNSeniorious000/dotenv.pth
Requires-Dist: python-dotenv
